genetools/__init__.py
genetools/arrays.py
genetools/helpers.py
genetools/palette.py
genetools/plots.py
genetools/scanpy_helpers.py
genetools/stats.py
genetools-0.7.5.dist-info/LICENSE
genetools-0.7.5.dist-info/METADATA
genetools-0.7.5.dist-info/WHEEL
genetools-0.7.5.dist-info/top_level.txt
genetools-0.7.5.dist-info/RECORD
