Metadata-Version: 2.1
Name: genetools
Version: 0.7.5
Summary: General genetics/genomics utilities.
Home-page: https://github.com/maximz/genetools
Author: Maxim Zaslavsky
Author-email: maxim@maximz.com
License: MIT license
Keywords: genetools
Classifier: Development Status :: 2 - Pre-Alpha
Classifier: Intended Audience :: Developers
Classifier: License :: OSI Approved :: MIT License
Classifier: Natural Language :: English
Classifier: Programming Language :: Python :: 3
Classifier: Programming Language :: Python :: 3.8
Requires-Python: >=3.8
License-File: LICENSE
Requires-Dist: numpy
Requires-Dist: matplotlib
Requires-Dist: pandas
Requires-Dist: seaborn
Requires-Dist: scikit-learn
Requires-Dist: joblib
Requires-Dist: scipy
Provides-Extra: scanpy
Requires-Dist: scanpy ; extra == 'scanpy'
